MANIFEST.in
README.md
setup.py
colored_with_contactform/__init__.py
colored_with_contactform/babel.cfg
colored_with_contactform/messages.pot
colored_with_contactform.egg-info/PKG-INFO
colored_with_contactform.egg-info/SOURCES.txt
colored_with_contactform.egg-info/dependency_links.txt
colored_with_contactform.egg-info/requires.txt
colored_with_contactform.egg-info/top_level.txt
colored_with_contactform/static/css/lang_ar.css
colored_with_contactform/static/css/lang_ar.css.map
colored_with_contactform/static/css/main.css
colored_with_contactform/static/css/main.css.map
colored_with_contactform/static/css/styles.css
colored_with_contactform/static/css/styles.css.map
colored_with_contactform/static/fonts/LibreBaskerville-Bold.ttf
colored_with_contactform/static/fonts/LibreBaskerville-Italic.ttf
colored_with_contactform/static/fonts/LibreBaskerville-Regular.ttf
colored_with_contactform/static/fonts/OFL.txt
colored_with_contactform/static/js/main.js
colored_with_contactform/static/js/html5shiv/html5shiv-printshiv.js
colored_with_contactform/static/js/html5shiv/html5shiv-printshiv.min.js
colored_with_contactform/static/js/html5shiv/html5shiv.js
colored_with_contactform/static/js/html5shiv/html5shiv.min.js
colored_with_contactform/static/scss/_fonts.scss
colored_with_contactform/static/scss/_globals.scss
colored_with_contactform/static/scss/_helper.scss
colored_with_contactform/static/scss/_highlight.scss
colored_with_contactform/static/scss/_reset.scss
colored_with_contactform/static/scss/_typography.scss
colored_with_contactform/static/scss/_variables.scss
colored_with_contactform/static/scss/lang_ar.scss
colored_with_contactform/static/scss/main.scss
colored_with_contactform/static/scss/modules/_form.scss
colored_with_contactform/static/scss/modules/_menu.scss
colored_with_contactform/templates/analytics.html
colored_with_contactform/templates/archives.html
colored_with_contactform/templates/article.html
colored_with_contactform/templates/article_infos.html
colored_with_contactform/templates/article_old.html
colored_with_contactform/templates/author.html
colored_with_contactform/templates/authors.html
colored_with_contactform/templates/base.html
colored_with_contactform/templates/categories.html
