Metadata-Version: 2.1
Name: colored-with-contactform
Version: 1.0.2
Summary: Colored theme with contact form
Home-page: https://github.com/abderrahimsoumer/pelican-hardweb-theme
Author: Abderrahim soumer
Author-email: contact@hardweb.dev
Maintainer: Abderrahim soumer
Maintainer-email: contact@hardweb.dev
License: MIT
Platform: UNKNOWN
Classifier: Development Status :: 3 - Alpha
Classifier: Framework :: Pelican :: Themes
Classifier: License :: OSI Approved :: MIT License
Classifier: Programming Language :: Python :: 3 :: Only
